Metadata-Version: 1.1
Name: PyWhist
Version: 0.1
Summary: A rather primitive bridge game
Home-page: http://practicealgebra.net/pywhist
Author: Andrew Warshall
Author-email: warshall@99main.com
License: Eclipse Public License
Platform: UNKNOWN
Classifier: Development Status :: 3 - Alpha
Classifier: Intended Audience :: End Users/Desktop
Classifier: Operating System :: OS Independent
Classifier: Programming Language :: Python :: 3
Classifier: Topic :: Games/Entertainment
Classifier: License :: OSI Approved
